centapp/__init__.py
centapp/centapp.py
centapp-1.0.1.dist-info/LICENSE
centapp-1.0.1.dist-info/METADATA
centapp-1.0.1.dist-info/WHEEL
centapp-1.0.1.dist-info/top_level.txt
centapp-1.0.1.dist-info/RECORD
