Metadata-Version: 2.1
Name: centapp
Version: 1.0.1
Summary: Python client library for interacting with CentApp API
Home-page: https://github.com/hteppl/centapp-sdk-python
Author: hteppl
Author-email: hteppl.dev@gmail.com
Keywords: python,api,sdk,payments,centapp
Classifier: Programming Language :: Python :: 3.10
Classifier: License :: OSI Approved :: MIT License
Classifier: Operating System :: OS Independent
Requires-Python: >=3.7
License-File: LICENSE
Requires-Dist: requests
